ethos/__init__.py
ethos/ethos_objects.py
ethos/ethos_client/__init__.py
ethos/ethos_client/client.py
ethos/ethos_client/errors.py
ethos/ethos_client/types.py
ethos/ethos_client/api/__init__.py
ethos/ethos_client/api/blobs/__init__.py
ethos/ethos_client/api/blobs/create_blob.py
ethos/ethos_client/api/blobs/get_blob.py
ethos/ethos_client/api/blobs/sync_blob_from_datasource.py
ethos/ethos_client/api/data_science/__init__.py
ethos/ethos_client/api/data_science/proxy_inference.py
ethos/ethos_client/api/datasources/__init__.py
ethos/ethos_client/api/datasources/get_datasources.py
ethos/ethos_client/api/documents/__init__.py
ethos/ethos_client/api/documents/create_document.py
ethos/ethos_client/api/documents/get_document.py
ethos/ethos_client/api/documents/get_document_versions.py
ethos/ethos_client/api/documents/get_documents.py
ethos/ethos_client/api/documents/update_document.py
ethos/ethos_client/api/events/__init__.py
ethos/ethos_client/api/events/get_events.py
ethos/ethos_client/api/folders/__init__.py
ethos/ethos_client/api/folders/create_folder.py
ethos/ethos_client/api/folders/get_folder.py
ethos/ethos_client/api/folders/get_folders.py
ethos/ethos_client/api/folders/update_folder.py
ethos/ethos_client/api/governed_objects/__init__.py
ethos/ethos_client/api/governed_objects/create_governed_object.py
ethos/ethos_client/api/governed_objects/get_governed_object.py
ethos/ethos_client/api/governed_objects/get_governed_object_metadata.py
ethos/ethos_client/api/governed_objects/get_governed_object_metadata_versions.py
ethos/ethos_client/api/governed_objects/get_governed_object_versions.py
ethos/ethos_client/api/governed_objects/get_governed_objects.py
ethos/ethos_client/api/governed_objects/update_governed_object.py
ethos/ethos_client/api/governed_objects/update_governed_object_metadata.py
ethos/ethos_client/api/governed_types/__init__.py
ethos/ethos_client/api/governed_types/create_governed_type.py
ethos/ethos_client/api/governed_types/create_governed_type_field.py
ethosai-0.1.8.dist-info/METADATA
ethosai-0.1.8.dist-info/WHEEL
ethosai-0.1.8.dist-info/licenses/LICENSE
ethosai-0.1.8.dist-info/RECORD
