Metadata-Version: 2.3
Name: ethosai
Version: 0.1.8
Summary: Ethos SDK for Python
Author-email: Ethos AI <sdk-owners@ethosai.com>
License-File: LICENSE
Classifier: License :: OSI Approved :: MIT License
Classifier: Operating System :: OS Independent
Classifier: Programming Language :: Python :: 3
Requires-Python: >=3.9
Requires-Dist: attrs>=21.3.0
Requires-Dist: httpx<0.28.0,>=0.20.0
Requires-Dist: pandas
Requires-Dist: pydantic<3,>=1.10.5
Requires-Dist: python-dateutil>=2.8.0
Requires-Dist: urllib3<2.3.0,>=1.25.3
